cellarr_frame/__init__.py
cellarr_frame/base.py
cellarr_frame/dense.py
cellarr_frame/helpers.py
cellarr_frame/sparse.py
cellarr_frame-0.0.1.dist-info/licenses/LICENSE.txt
cellarr_frame-0.0.1.dist-info/METADATA
cellarr_frame-0.0.1.dist-info/WHEEL
cellarr_frame-0.0.1.dist-info/top_level.txt
cellarr_frame-0.0.1.dist-info/RECORD
