Metadata-Version: 2.4
Name: cellarr-frame
Version: 0.0.1
Summary: A high-level Python package for managing DataFrames using TileDB as a backing store
Home-page: https://github.com/CellArr/cellarr-frame
Author: Jayaram Kancherla
Author-email: jayaram.kancherla@gmail.com
License: MIT
Project-URL: Documentation, https://github.com/CellArr/cellarr-frame
Project-URL: Source, https://github.com/CellArr/cellarr-frame
Platform: any
Classifier: Development Status :: 4 - Beta
Classifier: Programming Language :: Python
Requires-Python: >=3.9
License-File: LICENSE.txt
Requires-Dist: importlib-metadata; python_version < "3.8"
Requires-Dist: cellarr-array>=0.3.2
Requires-Dist: pandas
Requires-Dist: numpy
Requires-Dist: pyarrow
Requires-Dist: tiledb
Provides-Extra: testing
Requires-Dist: setuptools; extra == "testing"
Requires-Dist: pytest; extra == "testing"
Requires-Dist: pytest-cov; extra == "testing"
Dynamic: license-file
